pipexam/__init__.py
pipexam/lib.py
pipexam-0.0.1.dist-info/DESCRIPTION.rst
pipexam-0.0.1.dist-info/METADATA
pipexam-0.0.1.dist-info/RECORD
pipexam-0.0.1.dist-info/WHEEL
pipexam-0.0.1.dist-info/metadata.json
pipexam-0.0.1.dist-info/top_level.txt
