Metadata-Version: 2.0
Name: pipexam
Version: 0.0.1
Summary: just a simple test
Home-page: https://github.com/pypa/sampleproject
Author: lijinchao2007
Author-email: lijinchao2007@163.com
License: MIT License
Keywords: pip,exam
Platform: any
Requires-Dist: simplejson (>=1.1)
